skyvern_langchain/__init__.py
skyvern_langchain/agent.py
skyvern_langchain/client.py
skyvern_langchain/py.typed
skyvern_langchain/schema.py
skyvern_langchain/settings.py
skyvern_langchain-0.2.1.dist-info/METADATA
skyvern_langchain-0.2.1.dist-info/WHEEL
skyvern_langchain-0.2.1.dist-info/RECORD
