Metadata-Version: 2.4
Name: skyvern-langchain
Version: 0.2.1
Author-email: lawyzheng <lawy@skyvern.com>
Requires-Python: <3.14,>=3.11
Requires-Dist: langchain-core>=0.3.81
Requires-Dist: langchain<0.4,>=0.3.19
Requires-Dist: skyvern>=0.2.0
Requires-Dist: urllib3>=2.6.0
